LICENSE
README.md
setup.py
chess_engine_ozerm/ChessEngine.py
chess_engine_ozerm/__init__.py
chess_engine_ozerm.egg-info/PKG-INFO
chess_engine_ozerm.egg-info/SOURCES.txt
chess_engine_ozerm.egg-info/dependency_links.txt
chess_engine_ozerm.egg-info/top_level.txt