Metadata-Version: 2.1
Name: chess-engine-ozerm
Version: 0.1
Summary: Chess Engine for Python
Home-page: https://github.com/ozermehmett/chess_engine
Author: ozerm
Author-email: ozermehmet911@gmail.com
License: MIT
Keywords: CHESS,ENGINE
Classifier: Intended Audience :: Developers
Classifier: Topic :: Software Development :: Build Tools
Classifier: License :: OSI Approved :: MIT License
Classifier: Programming Language :: Python :: 3
Classifier: Programming Language :: Python :: 3.4
Classifier: Programming Language :: Python :: 3.5
Classifier: Programming Language :: Python :: 3.6
Classifier: Programming Language :: Python :: 3.7
Classifier: Programming Language :: Python :: 3.8
Classifier: Programming Language :: Python :: 3.9
Classifier: Programming Language :: Python :: 3.10
Classifier: Programming Language :: Python :: 3.11
License-File: LICENSE
